UzbekLemma/UzbekLemma.py
UzbekLemma/__init__.py
UzbekLemma/suzlar/istisnolar.txt
UzbekLemma/suzlar/kfsq.txt
UzbekLemma/suzlar/mustaqil__fel.txt
UzbekLemma/suzlar/mustaqil__olmosh.txt
UzbekLemma/suzlar/mustaqil__ot.txt
UzbekLemma/suzlar/mustaqil__ravish.txt
UzbekLemma/suzlar/mustaqil__sifat.txt
UzbekLemma/suzlar/mustaqil__son.txt
UzbekLemma/suzlar/oraliq__modal.txt
UzbekLemma/suzlar/oraliq__taqlid.txt
UzbekLemma/suzlar/oraliq__undov.txt
UzbekLemma/suzlar/yordamchi__boglovchi.txt
UzbekLemma/suzlar/yordamchi__komakchi.txt
UzbekLemma/suzlar/yordamchi__yuklama.txt
UzbekLemma-1.2.dist-info/METADATA
UzbekLemma-1.2.dist-info/WHEEL
UzbekLemma-1.2.dist-info/top_level.txt
UzbekLemma-1.2.dist-info/RECORD
