Metadata-Version: 2.1
Name: UzbekLemma
Version: 1.2
Summary: Finds the lemma of Uzbek words
Home-page: https://github.com/ddasturbek/UzbekLemma
Author-email: sobirovogabek0409@gmail.com
Classifier: Programming Language :: Python :: 3
Classifier: License :: OSI Approved :: MIT License
Classifier: Operating System :: OS Independent
Requires-Python: >=3.6
